turbojpeg.cpython-311-aarch64-linux-gnu.so
turbojpeg_rpi.libs/libturbojpeg-a0107d08.so.0.4.0
turbojpeg_rpi-0.0.3.dist-info/METADATA
turbojpeg_rpi-0.0.3.dist-info/WHEEL
turbojpeg_rpi-0.0.3.dist-info/top_level.txt
turbojpeg_rpi-0.0.3.dist-info/RECORD
