Metadata-Version: 2.4
Name: turbojpeg-rpi
Version: 0.0.3
Summary: Python bindungs for libjpeg-turbo using pybind11
Author: raghavauppuluri13
Project-URL: Homepage, https://github.com/Dobatymo/turbojpeg-python
Classifier: Operating System :: OS Independent
Classifier: Programming Language :: Python :: 3 :: Only
Classifier: Programming Language :: Python :: 3.7
Classifier: Programming Language :: Python :: 3.8
Classifier: Programming Language :: Python :: 3.9
Classifier: Programming Language :: Python :: 3.10
Classifier: Programming Language :: Python :: 3.11
Classifier: Programming Language :: Python :: 3.12
Requires-Python: >=3.7
Provides-Extra: test
Requires-Dist: numpy; extra == "test"
Requires-Dist: pillow; extra == "test"
Requires-Dist: scikit-image; extra == "test"
